{
  "data": {
    "attachments": {},
    "author_id": "1498354035854053377",
    "conversation_id": "1810233621196034465",
    "created_at": "2024-07-08T10:58:49.000Z",
    "edit_controls": {
      "editable_until": "2024-07-08T11:58:49.000Z",
      "edits_remaining": 5,
      "is_edit_eligible": false
    },
    "edit_history_tweet_ids": [
      "1810267290472243397"
    ],
    "entities": {
      "mentions": [
        {
          "end": 14,
          "id": "1429829081684537345",
          "start": 0,
          "username": "Rabbubble550W"
        }
      ]
    },
    "geo": {},
    "id": "1810267290472243397",
    "in_reply_to_user_id": "1429829081684537345",
    "lang": "ja",
    "possibly_sensitive": false,
    "public_metrics": {
      "bookmark_count": 0,
      "impression_count": 0,
      "like_count": 0,
      "quote_count": 0,
      "reply_count": 0,
      "retweet_count": 0
    },
    "referenced_tweets": [
      {
        "id": "1810233621196034465",
        "type": "replied_to"
      }
    ],
    "reply_settings": "everyone",
    "text": "@Rabbubble550W 困惑"
  },
  "includes": {
    "tweets": [
      {
        "attachments": {},
        "author_id": "1498354035854053377",
        "conversation_id": "1810233621196034465",
        "created_at": "2024-07-08T10:58:49.000Z",
        "edit_controls": {
          "editable_until": "2024-07-08T11:58:49.000Z",
          "edits_remaining": 5,
          "is_edit_eligible": false
        },
        "edit_history_tweet_ids": [
          "1810267290472243397"
        ],
        "entities": {
          "mentions": [
            {
              "end": 14,
              "id": "1429829081684537345",
              "start": 0,
              "username": "Rabbubble550W"
            }
          ]
        },
        "geo": {},
        "id": "1810267290472243397",
        "in_reply_to_user_id": "1429829081684537345",
        "lang": "ja",
        "possibly_sensitive": false,
        "public_metrics": {
          "bookmark_count": 0,
          "impression_count": 0,
          "like_count": 0,
          "quote_count": 0,
          "reply_count": 0,
          "retweet_count": 0
        },
        "referenced_tweets": [
          {
            "id": "1810233621196034465",
            "type": "replied_to"
          }
        ],
        "reply_settings": "everyone",
        "text": "@Rabbubble550W 困惑"
      },
      {
        "attachments": {
          "media_keys": [
            "3_1810233600186646528"
          ]
        },
        "author_id": "1429829081684537345",
        "conversation_id": "1810233621196034465",
        "created_at": "2024-07-08T08:45:02.000Z",
        "edit_controls": {
          "editable_until": "2024-07-08T09:45:02.000Z",
          "edits_remaining": 5,
          "is_edit_eligible": true
        },
        "edit_history_tweet_ids": [
          "1810233621196034465"
        ],
        "entities": {
          "urls": [
            {
              "display_url": "pic.twitter.com/iO6U8trKgN",
              "end": 26,
              "expanded_url": "https://twitter.com/Rabbubble550W/status/1810233621196034465/photo/1",
              "media_key": "3_1810233600186646528",
              "start": 3,
              "url": "https://t.co/iO6U8trKgN"
            }
          ]
        },
        "geo": {},
        "id": "1810233621196034465",
        "lang": "zh",
        "possibly_sensitive": false,
        "public_metrics": {
          "bookmark_count": 1,
          "impression_count": 18636,
          "like_count": 168,
          "quote_count": 19,
          "reply_count": 237,
          "retweet_count": 2
        },
        "reply_settings": "everyone",
        "text": "开盒 https://t.co/iO6U8trKgN"
      }
    ],
    "users": [
      {
        "created_at": "2022-02-28T17:47:35.000Z",
        "description": "业余作者 英语不好 ex madman",
        "id": "1498354035854053377",
        "location": "Elysium",
        "name": "铜与蜡",
        "profile_image_url": "https://pbs.twimg.com/profile_images/1583077390455971840/VFX6dQZe_normal.jpg",
        "protected": false,
        "public_metrics": {
          "followers_count": 53,
          "following_count": 247,
          "like_count": 10364,
          "listed_count": 46,
          "tweet_count": 358
        },
        "username": "lijunyi87429205",
        "verified": false
      },
      {
        "created_at": "2021-08-23T15:33:28.000Z",
        "description": "常驻东莞，欢迎互fo ，转推、段子梗图不代表本人的意见 ，最最最最喜欢对咱最好的人 @vu_yoyo",
        "entities": {
          "description": {
            "mentions": [
              {
                "end": 50,
                "start": 42,
                "username": "vu_yoyo"
              }
            ]
          }
        },
        "id": "1429829081684537345",
        "location": "Guangdong",
        "name": "早露泡泡兔",
        "pinned_tweet_id": "1809623415680278624",
        "profile_image_url": "https://pbs.twimg.com/profile_images/1748554253072003072/fMXc918b_normal.jpg",
        "protected": false,
        "public_metrics": {
          "followers_count": 7329,
          "following_count": 6659,
          "like_count": 71228,
          "listed_count": 29,
          "tweet_count": 59362
        },
        "username": "Rabbubble550W",
        "verified": true
      }
    ]
  }
}