{
  "data": {
    "article": {},
    "attachments": {},
    "author_id": "1498354035854053377",
    "conversation_id": "2049435539737325589",
    "created_at": "2026-05-01T00:48:38.000Z",
    "edit_controls": {
      "editable_until": "2026-05-01T01:48:38.000Z",
      "edits_remaining": 5,
      "is_edit_eligible": false
    },
    "edit_history_tweet_ids": [
      "2050014498048864675"
    ],
    "entities": {
      "mentions": [
        {
          "end": 11,
          "id": "1637972200371224577",
          "start": 0,
          "username": "P0larstern"
        },
        {
          "end": 22,
          "id": "1729436345913995265",
          "start": 12,
          "username": "p1NRed1_A"
        }
      ]
    },
    "geo": {},
    "id": "2050014498048864675",
    "in_reply_to_user_id": "1637972200371224577",
    "lang": "zh",
    "note_tweet": {
      "entities": {}
    },
    "possibly_sensitive": false,
    "public_metrics": {
      "bookmark_count": 0,
      "impression_count": 0,
      "like_count": 0,
      "quote_count": 0,
      "reply_count": 0,
      "retweet_count": 0
    },
    "referenced_tweets": [
      {
        "id": "2049892006999318747",
        "type": "replied_to"
      }
    ],
    "reply_settings": "everyone",
    "text": "@P0larstern @p1NRed1_A 当然可以的，请您随意"
  },
  "includes": {
    "tweets": [
      {
        "article": {},
        "attachments": {},
        "author_id": "1498354035854053377",
        "conversation_id": "2049435539737325589",
        "created_at": "2026-05-01T00:48:38.000Z",
        "edit_controls": {
          "editable_until": "2026-05-01T01:48:38.000Z",
          "edits_remaining": 5,
          "is_edit_eligible": false
        },
        "edit_history_tweet_ids": [
          "2050014498048864675"
        ],
        "entities": {
          "mentions": [
            {
              "end": 11,
              "id": "1637972200371224577",
              "start": 0,
              "username": "P0larstern"
            },
            {
              "end": 22,
              "id": "1729436345913995265",
              "start": 12,
              "username": "p1NRed1_A"
            }
          ]
        },
        "geo": {},
        "id": "2050014498048864675",
        "in_reply_to_user_id": "1637972200371224577",
        "lang": "zh",
        "note_tweet": {
          "entities": {}
        },
        "possibly_sensitive": false,
        "public_metrics": {
          "bookmark_count": 0,
          "impression_count": 0,
          "like_count": 0,
          "quote_count": 0,
          "reply_count": 0,
          "retweet_count": 0
        },
        "referenced_tweets": [
          {
            "id": "2049892006999318747",
            "type": "replied_to"
          }
        ],
        "reply_settings": "everyone",
        "text": "@P0larstern @p1NRed1_A 当然可以的，请您随意"
      },
      {
        "article": {},
        "attachments": {},
        "author_id": "1637972200371224577",
        "conversation_id": "2049435539737325589",
        "created_at": "2026-04-30T16:41:54.000Z",
        "edit_controls": {
          "editable_until": "2026-04-30T17:41:54.000Z",
          "edits_remaining": 5,
          "is_edit_eligible": false
        },
        "edit_history_tweet_ids": [
          "2049892006999318747"
        ],
        "entities": {
          "mentions": [
            {
              "end": 16,
              "id": "1498354035854053377",
              "start": 0,
              "username": "lijunyi87429205"
            },
            {
              "end": 27,
              "id": "1729436345913995265",
              "start": 17,
              "username": "p1NRed1_A"
            }
          ]
        },
        "geo": {},
        "id": "2049892006999318747",
        "in_reply_to_user_id": "1498354035854053377",
        "lang": "zh",
        "note_tweet": {
          "entities": {}
        },
        "possibly_sensitive": false,
        "public_metrics": {
          "bookmark_count": 0,
          "impression_count": 5,
          "like_count": 1,
          "quote_count": 0,
          "reply_count": 1,
          "retweet_count": 0
        },
        "referenced_tweets": [
          {
            "id": "2049865259918504321",
            "type": "replied_to"
          }
        ],
        "reply_settings": "everyone",
        "text": "@lijunyi87429205 @p1NRed1_A 等我练好字的话可以把意洵的诗歌摘录下来吗！"
      }
    ],
    "users": [
      {
        "created_at": "2022-02-28T17:47:35.000Z",
        "description": "生理男性 酒神崇拜/ 非专业作者，创作：诗 悲喜剧 短篇小说 / 可以用您觉得任何合适的指代，但如果把我当作朋友，请用“意洵”这个名字吧/",
        "id": "1498354035854053377",
        "location": "Elysium",
        "name": "意之意",
        "profile_image_url": "https://pbs.twimg.com/profile_images/1583077390455971840/VFX6dQZe_normal.jpg",
        "protected": false,
        "public_metrics": {
          "followers_count": 146,
          "following_count": 377,
          "like_count": 62737,
          "listed_count": 8,
          "media_count": 42,
          "tweet_count": 1679
        },
        "username": "lijunyi87429205",
        "verified": false
      },
      {
        "created_at": "2023-03-21T00:19:55.000Z",
        "description": "前世@nejamais1 | 男的 | 可以叫我小天 | 水仙 | 双相",
        "entities": {
          "description": {
            "mentions": [
              {
                "end": 12,
                "start": 2,
                "username": "nejamais1"
              }
            ]
          }
        },
        "id": "1637972200371224577",
        "name": "P0larstern",
        "profile_image_url": "https://pbs.twimg.com/profile_images/2014033112875798528/fzYQKz3U_normal.jpg",
        "protected": false,
        "public_metrics": {
          "followers_count": 83,
          "following_count": 86,
          "like_count": 1630,
          "listed_count": 0,
          "media_count": 46,
          "tweet_count": 1101
        },
        "username": "P0larstern",
        "verified": false
      },
      {
        "created_at": "2023-11-28T09:45:45.000Z",
        "description": "死全家星人",
        "id": "1729436345913995265",
        "location": "天国",
        "name": "咕咚",
        "pinned_tweet_id": "1909930064051134531",
        "profile_image_url": "https://pbs.twimg.com/profile_images/2036750324674048000/QVQcKLvc_normal.jpg",
        "protected": false,
        "public_metrics": {
          "followers_count": 425,
          "following_count": 546,
          "like_count": 1651,
          "listed_count": 3,
          "media_count": 348,
          "tweet_count": 5989
        },
        "username": "p1NRed1_A",
        "verified": false
      }
    ]
  }
}